lfxai/__init__.py
lfxai/version.py
lfxai/explanations/__init__.py
lfxai/explanations/examples.py
lfxai/explanations/features.py
lfxai/models/__init__.py
lfxai/models/base.py
lfxai/models/images.py
lfxai/models/losses.py
lfxai/models/pretext.py
lfxai/models/time_series.py
lfxai/utils/__init__.py
lfxai/utils/datasets.py
lfxai/utils/feature_attribution.py
lfxai/utils/influence.py
lfxai/utils/math.py
lfxai/utils/metrics.py
lfxai/utils/visualize.py
lfxai-0.1.1.dist-info/METADATA
lfxai-0.1.1.dist-info/WHEEL
lfxai-0.1.1.dist-info/top_level.txt
lfxai-0.1.1.dist-info/RECORD
