Metadata-Version: 2.1
Name: lfxai
Version: 0.1.1
Summary: A framework to explain the latent representations of unsupervised black-box models with the help of usual feature importance and example-based methods.
Home-page: UNKNOWN
Author: Jonathan Crabbé
Author-email: jc2133@cam.ac.uk
License: MIT
Platform: any
Classifier: Programming Language :: Python :: 3
Classifier: Topic :: Scientific/Engineering :: Artificial Intelligence
Classifier: Intended Audience :: Healthcare Industry
Classifier: Operating System :: OS Independent
Requires-Python: >=3.6
Requires-Dist: torch
Requires-Dist: torchvision
Requires-Dist: captum
Requires-Dist: hydra-core
Requires-Dist: numpy
Requires-Dist: pandas
Requires-Dist: scikit-image
Requires-Dist: scikit-learn
Requires-Dist: scipy
Requires-Dist: seaborn
Requires-Dist: tabulate
Requires-Dist: tqdm
Requires-Dist: wget
Requires-Dist: matplotlib
Requires-Dist: importlib-metadata ; python_version < "3.8"
Provides-Extra: testing
Requires-Dist: setuptools ; extra == 'testing'
Requires-Dist: pytest ; extra == 'testing'
Requires-Dist: pytest-cov ; extra == 'testing'
Requires-Dist: jupyter ; extra == 'testing'
Requires-Dist: notebook ; extra == 'testing'
Requires-Dist: pre-commit ; extra == 'testing'
